{"id":324,"examTicketId":15575,"imageId":null,"question":"Reliability is:","answers":[{"answer":"The ability of a machine to perform its function at a high level","answerNumbering":4},{"answer":"The ability to keep its working tools operational without failing in a given stretch of time","answerNumbering":3},{"answer":"The ability to stay firm while moving ","answerNumbering":2},{"answer":"The ability of a machine to perform its function while maintaining its performance characteristics unchanged","answerNumbering":1}],"rightAnswer":1,"explanation":"\"საიმედობა წარმოადგენს მანქანის თვისებას, შეინარჩუნოს მოცემული ფუნქციის შესრულების უნარი საექსპლოატაციო მაჩვენებლების შეცვლის გარეშე.\""}