{"id":160,"examTicketId":15333,"imageId":null,"question":"F,ekmljpth fecehffy b7fkjv:","answers":[{"answer":"Fvq`s;`8f fim0s[htb fysi` fec flekfhtb fei`f6` 3%0  tb]fys  bh[`fpfh","answerNumbering":3},{"answer":"Fvq`s;`8f fim0s[htb fysi` fec flekfhtb fei`f6` 2%0  tb]fys bh[`fpfh","answerNumbering":2},{"answer":"Fvq`s;`8f fim0s[htb fysi` fec flekfhtb fei`f6` 150  tb]fys   bh[`fpfh","answerNumbering":1}],"rightAnswer":2,"explanation":"\"ბულდოზერის მუშაობა დაუშვევებელია, თუ ფრთის აწევა და გრუნტის დამუშავება გრძივი დახრილობისას 20°-ზე მეტია.\\r\\n \\r\\n\""}