{"id":318,"examTicketId":15569,"imageId":null,"question":"Fnhf6njh fhys7`fuf pkfimf6`uskj fcbcntvf6`f bfh,fye?","answers":[{"answer":"Fv[flfhf fcbcntvf> fhys7`fhf fcbcntvf> ffyrskfhf fcbcntvf> fhwwfrhf fcbcntvf> fbvflfhf fcbcntvf","answerNumbering":3},{"answer":"Fbkf0`fhf fcbcntvf> fbkfwfkfhf fcbcntvf> fh0,ffhf fcbcntvf> fhkfifhf fcbcntvf","answerNumbering":2},{"answer":"Fh0`hfn` fcbcntvf> fhkfifhf fcbcntvf> fptb0syn` cbcntvf> fh[mi`fi`fuf fcbcntvf> fkchfn` cbcntvf","answerNumbering":1}],"rightAnswer":1,"explanation":"\"ტრაქტორის ძრავა შედგება კვების სისტემის, ანთების სისტემის, შეზეთვის სისტემის, გაგრილების სისტემისა და გაშვების სისტემისაგან.\""}