{"id":331,"examTicketId":15583,"imageId":null,"question":"Fnt[yjkjubfn` vfimsyf6`f f=fqf[`sn` 0fuskfimfps fyshhf hsvjeg bfim0fytbef faf6njh6`f:","answers":[{"answer":"f. frjycnhe6wbfn`> ,. f[fh[`fhfn`","answerNumbering":4},{"answer":"f. f9cf,fhf–f]fbhn`> ,. frjycnhe6wbfn`","answerNumbering":3},{"answer":"f. f9cf,fhf–f]fbhn`> ,. frjycnhe6wbfn`> u. f[fh[`fhfn`","answerNumbering":2},{"answer":"f. fb=rffhfn`> ,. fy[fv8fn`> d. frjycnhe6wbfn`","answerNumbering":1}],"rightAnswer":2,"explanation":"\"ტექნოლოგიური მანქანების ხვედრით წინააღმდეგობაზე მოქმედებენ შემდეგი ფაქტორები:\\r\\n ა. ბუნებრივ-კლიმატური;\\r\\n ბ. კონსტრუქციული;\\r\\n გ. საექსპლოატაციო;\\r\\n\""}