{"id":212,"examTicketId":15501,"imageId":null,"question":"Ոլորանով երթևեկելիս, պտտման կենտրոնից մինչև շրջադարձի կենտրոնի հակառակ կողմում շարժվող առջևի և շրջադարձի կողմում շարժվող հետին անիվները տարված շառավիղների տարբերությունը կոչվում է.","answers":[{"answer":"Ավտոմեքենայի թույլատրելի միջտարածություն:","answerNumbering":3},{"answer":"Ավտոմեքենայի դինամիկական միջանցք:","answerNumbering":2},{"answer":"Ավտոմեքենայի շրջադարձի շառավիղ:","answerNumbering":1}],"rightAnswer":2,"explanation":"\" მოსახვევში მოძრაობისას სატვირთო ავტომობილებისა და ავტობუსების მოძრაობისათვის საჭირო ზოლი მნიშვნელოვნად ფართოვდება. მოხვევისას ავტომობილის წინა თვლები იკავებს მოხვევის ცენტრის საწინააღმდეგო მხარეს, ხოლო ავტომობილის ან მისაბმელის უკანა თვლები მოხვევის ცენტრის მხარეს. მოხვევის ცენტრის საწინააღმდეგო მხარეს მოძრავი წინა და მოხვევის მხარეს მოძრავი უკანა თვლებამდე მოხვევის ცენტრიდან გავლებული რადიუსების სხვაობას ეწოდება ავტომობილის დინამიკური დერეფანი.\""}