{"id":508,"examTicketId":14525,"imageId":373,"question":"Տրված իրադրությունում, ո՞ր տրանսպորտային միջոցի վարորդն է խախտում  ճանապարհային երթևեկության կանոնները, եթե  կամրջի վրա ուղևորների նստեցման նպատակով թեթև մարդատար  ավտոմեքենան  սլաքի ուղղությամբ հետընթաց է երթևեկում,  իսկ մոտոցիկլը սլաքի ուղղությամբ հետադարձ է կատարում:","answers":[{"answer":"Երկու տրանսպորտային միջոցների վարորդներն էլ:","answerNumbering":4},{"answer":"Ոչ մի տրանսպորտային միջոցի վարորդ:","answerNumbering":3},{"answer":"Ավտոմեքենայի վարորդը:","answerNumbering":2},{"answer":"Մոտոցիկլի վարորդը:","answerNumbering":1}],"rightAnswer":4,"explanation":"\"„საგზაო მოძრაობის შესახებ“ საქართველოს კანონის 32-ე მუხლის მე-15 პუნქტის „გ“ ქვეპუნქტის  თანახმად, აკრძალულია სატრანსპორტო საშუალების მობრუნება ხიდზე, გზაგამტარზე, ესტაკადაზე და მათ ქვეშ.\\r\\n ამავე მუხლის მე-16 პუნქტის  თანახმად, მძღოლი, რომელიც მობრუნებას ან უკუსვლით მოძრაობას აპირებს, უნდა დარწმუნდეს, რომ მას შეუძლია ისე შეასრულოს ეს მანევრი, რომ საფრთხე არ შეუქმნას და ხელი არ შეუშალოს სხვა საგზაო მოძრაობის მონაწილეებს. აუცილებლობის შემთხვევაში მიზანშეწონილია სხვა პირის დახმარება. აკრძალულია უკუსვლით მოძრაობა გზაჯვარედინზე, ავტომაგისტრალზე და ამ მუხლის მე-15 პუნქტით განსაზღვრულ ადგილებში.\\r\\n\""}