{"id":682,"examTicketId":14794,"imageId":null,"question":"Օրվա   մութ ժամանակ, մեխանիկական տրանսպորտային միջոցի մոտակա և հեռահար լապտերների միաժամանակ շարքից դուրս գալու (հանգչելու) դեպքում, վարորդին արգելվում է.","answers":[{"answer":"Երթևեկել արհեստականորեն լուսավորված երկկողմ երթևեկությամբ ճանապարհով:","answerNumbering":3},{"answer":"Ցանկացած ճանապարհով երթևեկելը, անկախ նրանից  այնտեղ կա, թե`  չկա արհեստական լուսավորում:","answerNumbering":2},{"answer":"Այն ճանապարհով երթևեկելը, որտեղ չկա արհեստական լուսավորում:","answerNumbering":1}],"rightAnswer":1,"explanation":"\"„საგზაო მოძრაობის შესახებ“ საქართველოს კანონის მე-21-ე მუხლის მე-13 პუნქტის  თანახმად, მძღოლს ეკრძალება მოძრაობა მუშა სამუხრუჭო სისტემის, საჭის მექანიზმის, სატრანსპორტო საშუალებათა შემადგენლობაში მისაბმელი მოწყობილობის გაუმართაობისას, აგრეთვე დღე-ღამის ბნელ დროს ერთდროულად მწყობრიდან გამოსული (ჩამქრალი) ახლო და შორი განათების ფარებით (ან მათი არარსებობისას) ან/და უკანა საგაბარიტო სინათლეებით იმ გზაზე, რომელზედაც არ არის ხელოვნური განათება ან არასაკმარისი ხილვადობაა. მძღოლის მხარეს არსებული მინასაწმენდის უმოქმედობისას აკრძალულია მექანიკური სატრანსპორტო საშუალების მართვა ნისლის, წვიმისა და თოვის დროს.\""}