{"id":885,"examTicketId":15759,"imageId":null,"question":"Ուղիղ ճանապարhով, երկար ժամանակվա ընթացքում   բարձր արագությամբ երթևեկելիս` տրանսպորտային միջոցի  արագությունը վարորդն ընկալում է.","answers":[{"answer":" Ավելի բարձր, քան իրականում է:  ","answerNumbering":1},{"answer":" Ավելի ցածր, քան իրականում է:  ","answerNumbering":2},{"answer":" Ինչպես իրականում է:  ","answerNumbering":3}],"rightAnswer":2,"explanation":"\"სწორ გზაზე, ხანგრძლივი დროის განმავლობაში მაღალი სიჩქარით მოძრაობისას სატრანსპორტო საშუალების სიჩქარეს მძღოლი აღიქვამს უფრო ნაკლებად, ვიდრე სინამდვილეშია.\""}