{"id":439,"examTicketId":14499,"imageId":null,"question":"თუ საგზაო ნიშნებისა და საგზაო მონიშვნების მოთხოვნები ერთმანეთს ეწინააღმდეგება, მძღოლი ვალდებულია შეასრულოს:","answers":[{"answer":"საგზაო მონიშვნის მოთხოვნები","answerNumbering":2},{"answer":"საგზაო ნიშნების მოთხოვნები","answerNumbering":1}],"rightAnswer":1,"explanation":"\"„საგზაო მოძრაობის შესახებ“ საქართველოს კანონის 28-ე მუხლის მე-4   პუნქტის  თანახმად, თუ საგზაო ნიშნებისა და საგზაო მონიშვნების  მოთხოვნები ერთმანეთს ეწინააღმდეგება, მძღოლი ვალდებულია შეასრულოს საგზაო ნიშნების მოთხოვნები. \""}