{"id":168,"examTicketId":15220,"imageId":1229,"question":"С данных дорожных знаков, какой дает информацию, об общих ограничений скорости установленных на дорогах Грузии?","answers":[{"answer":"IV","answerNumbering":4},{"answer":"III","answerNumbering":3},{"answer":"II","answerNumbering":2},{"answer":"I","answerNumbering":1}],"rightAnswer":2,"explanation":"\"    „საგზაო მოძრაობის შესახებ“ საქართველოს კანონის პირველი დანართის მე-7 თავის (საინფორმაციო-მაჩვენებელი ნიშნები) 7.1 პუნქტის თანახმად, საგზაო ნიშანი  7.1 „მაქსიმალური სიჩქარის ზოგადი შეზღუდვები“ - იძლევა ინფორმაციას სიჩქარის ზოგადი შეზღუდვების თაობაზე, რომლებიც საგზაო მოძრაობის წესებით დადგენილია საქართველოს გზებზე. ნიშანი იდგმება საქართველოს ტერიტორიაზე შემოსასვლელში საკონტროლო გამშვებ პუნქტთან.\""}