{"id":713,"examTicketId":14794,"imageId":null,"question":"Изæрæй боны рухсмæ талынг рæстæджы, механикон транспортон фæрæзы æввахсмæ æмæ дардмæ рухсгæнæн фарæты æмрæстæджы ахуыссыны рæстæджы, скъæрæгæн бар нæй:","answers":[{"answer":"Кæцыфæнды фæндагыл змæлын, æнæкæсгæйæ  уымæ, ис æви нæ ууыл аразгæ рухсгæнæн","answerNumbering":2},{"answer":"Змæлд аразгæ рухсгæнæнæй дывæрсон змæлæн фæндагыл","answerNumbering":3},{"answer":"Уыцы фæндагыл змæлын, кæцыйыл нæй аразгæ рухсгæнæн","answerNumbering":1}],"rightAnswer":1,"explanation":"\"„საგზაო მოძრაობის შესახებ“ საქართველოს კანონის მე-21-ე მუხლის მე-13 პუნქტის  თანახმად, მძღოლს ეკრძალება მოძრაობა მუშა სამუხრუჭო სისტემის, საჭის მექანიზმის, სატრანსპორტო საშუალებათა შემადგენლობაში მისაბმელი მოწყობილობის გაუმართაობისას, აგრეთვე დღე-ღამის ბნელ დროს ერთდროულად მწყობრიდან გამოსული (ჩამქრალი) ახლო და შორი განათების ფარებით (ან მათი არარსებობისას) ან/და უკანა საგაბარიტო სინათლეებით იმ გზაზე, რომელზედაც არ არის ხელოვნური განათება ან არასაკმარისი ხილვადობაა. მძღოლის მხარეს არსებული მინასაწმენდის უმოქმედობისას აკრძალულია მექანიკური სატრანსპორტო საშუალების მართვა ნისლის, წვიმისა და თოვის დროს.\""}