{"id":710,"examTicketId":14849,"imageId":null,"question":"A median strip is ","answers":[{"answer":"A structurally-separated road component that separates adjacent roadways and is not meant for the movement of non-rail vehicles ","answerNumbering":3},{"answer":"Any of the longitudinal lanes on the roadway, whether having or not having a longitudinal marking ","answerNumbering":2},{"answer":"A road component usually used for the movement of non-rail vehicles","answerNumbering":1}],"rightAnswer":3,"explanation":"\" „საგზაო მოძრაობის შესახებ“ საქართველოს კანონის 5-ე მუხლის მე-9  პუნქტის თანახმად, გამყოფი ზოლი – კონსტრუქციულად გამოყოფილი გზის ელემენტი, რომელიც ყოფს მომიჯნავე სავალ ნაწილებს და არ არის განკუთვნილი მასზე ურელსო სატრანსპორტო საშუალების მოძრაობისათვის.\""}