{"id":190,"examTicketId":15366,"imageId":null,"question":"Цæуыны арæхстмæ гæсгæйæ скрепыртæ дих кæнынц?          ","answers":[{"answer":" Прицепон, æрдæгприцепон æмæ хæдтулгæ скрепыртыл. ","answerNumbering":2},{"answer":"Æрмæст хæдтулгæ æмæ прицепон скрепыртыл.","answerNumbering":3},{"answer":" Æрмæст прицепон æмæ æрдæгприцепон скрепыртыл.","answerNumbering":1}],"rightAnswer":2,"explanation":"\"გადაადგილების ხერხის მიხედვით სკრეპერები იყოფიან მისაბმელ, ნახევარმისაბმელ და თვითმავალ სკრეპერებად.\""}