{"id":299,"examTicketId":15550,"imageId":null,"question":"Кæм пайда кæнынц пърессгæнæнæй? ","answers":[{"answer":"Къадайæ æркарстгонд массæйы сисынæн æмæ быдыры мидæг мæкъуылтæ \r\nскæнынæн. \r\n","answerNumbering":2},{"answer":"Хосы кæнæ нартхоры хъæдтæй цъынатæ саразынæн","answerNumbering":3},{"answer":"Бахусгонд æмæ ног æркæрдгæ кæрдæджытæ фадыгæй æмæ къадайæ поцхи кæнынæн","answerNumbering":4},{"answer":"Хосы кæнæ нартхоры хъæды къадайæ сисынæн, пъресс кæнынæн æмæ пърессгонд массæйы бабæттынæн","answerNumbering":1}],"rightAnswer":1,"explanation":"\"წნეხამკრეფებს იყენებენ თივის ან ჩალის ღვარეულებიდან ასაკრეფად, დასაწნეხად და დაწნეხილი მასის შესაკვრელად.\""}