{"id":300,"examTicketId":15786,"imageId":null,"question":"Из нижеперечисленных, исправность какого узла должен регулярно проверять водитель?","answers":[{"answer":"Только механизм рулевого управления","answerNumbering":1},{"answer":"Только шины","answerNumbering":2},{"answer":"Только приборы наружнего освещения","answerNumbering":3},{"answer":"Всех узлов перечисленные в этом билете ","answerNumbering":4}],"rightAnswer":4,"explanation":"\"ავტომობილის მძღოლმა რეგულარულად უნდა შეამოწმოს როგორც საჭის მართვის მექანიზმის, ასევე საბურავების  და გარე სანათი ხელსაწყოების გამართულობა.\""}