{"id":5,"examTicketId":15048,"imageId":null,"question":"Bfyskfije ffv0fps fy[fh0f0s9 f=s f9schf f-fprhf bfprys tums fhys7`f8 fu`-fyqfhf b0fhfps f[fh[`fhf 7fkjbn:","answers":[{"answer":"Fvfimsyf,kf6`f ffbu`fn` hskfifhf [fhfn` hskfifhfi7f bpysrsvr`f fbfufhf","answerNumbering":4},{"answer":"Fvfi`shn` fkfifhfn` fhlshuf","answerNumbering":3},{"answer":"Fvfimsyf,kf6`f hskfifhf ffv0f-ffv0fkf h=frhtb hshw`fhtb","answerNumbering":2},{"answer":"F,;msn` fhlshuf","answerNumbering":1}],"rightAnswer":2,"explanation":"\" „საგზაო მოძრაობის შესახებ“ საქართველოს კანონის 48-ე მუხლის მე-3  პუნქტის თანახმად, დასახლებულ პუნქტში გასწრების განზრახვის შესახებ სხვა სატრანსპორტო საშუალების მძღოლის გასაფრთხილებლად შეიძლება ჩაირთოს მანათობელი სიგნალი დღე-ღამის ნათელ დროს ფარების შუქის პერიოდული, ხანმოკლე ჩართვა-გამორთვით, ხოლო დღე-ღამის ბნელ დროს – ფარების ახლო შუქის შორ შუქზე მრავალჯერადი გადართვით, დაუსახლებელ პუნქტში კი − ხმოვანი სიგნალის ნაცვლად ან მასთან ერთად.\""}