{"id":811,"examTicketId":15015,"imageId":null,"question":"Sert frenleyerek araç durdurması aşağıdakilerden hangi durumda izinlidir?","answers":[{"answer":"Sadece trafik lambasının kırmızı ve sarı ışıkların aynı zamanda yandığı takdirde.","answerNumbering":2},{"answer":"Sadece trafik kazasını kaçınma amacıyla. ","answerNumbering":3},{"answer":"İş bu testte belirtilen  herhangi bir durumda","answerNumbering":4},{"answer":"Sadece trafik görevlisinin durdurma talep ettiğinde.","answerNumbering":1}],"rightAnswer":3,"explanation":"\" „საგზაო მოძრაობის შესახებ“ საქართველოს კანონის 33-ე მუხლის მე-4 პუნქტის   თანახმად, მძღოლს ეკრძალება მკვეთრი დამუხრუჭება, გარდა საგზაო-სატრანსპორტო შემთხვევის თავიდან აცილების აუცილებლობით გამოწვეული დამუხრუჭებისა.\""}