{"id":144,"examTicketId":15248,"imageId":1257,"question":"Фæндаджы цæуæн хайыл дыдагъ пунктирон хахх бæрæг кæны:","answers":[{"answer":"Бынаты, цыран скъæрæг бахъæуæджы рæстæджы хъуамæ æрурома","answerNumbering":2},{"answer":"Реверсонæй æрбæстонгонд змæлды хæххыты арæнты","answerNumbering":3},{"answer":"Алвæндагыл (перекрестокыл) велосипеды фæндæгтæ","answerNumbering":1}],"rightAnswer":3,"explanation":"\" „საგზაო მოძრაობის შესახებ“ საქართველოს კანონის მე-2 დანართის პირველი თავის (ჰორიზონტალური მონიშვნა) 1.9  პუნქტის თანახმად, საგზაო მონიშვნა        1.9 აღნიშნავს რევერსულად მოწესრიგებული მოძრაობის ზოლის საზღვარს; ყოფს საპირისპირო მიმართულებით მოძრავ სატრანსპორტო ნაკადებს (როდესაც გამორთულია რევერსული შუქნიშანი) გზაზე, რომელიც რევერსულად წესრიგდება.\""}