{"id":131,"examTicketId":15296,"imageId":1136,"question":"Ո՞ր ուղղությամբ չի արգելվում ուսումնական ավտոմեքենայի երթևեկությունը, եթե ղեկի մոտ նստած է աշակերտ:","answers":[{"answer":"Ինչպես A, այնպես էլ B ուղղությամբ:","answerNumbering":3},{"answer":"B ուղղությամբ:","answerNumbering":2},{"answer":"A ուղղությամբ:","answerNumbering":1}],"rightAnswer":3,"explanation":"\"  „საგზაო მოძრაობის შესახებ“ საქართველოს კანონის 38-ე მუხლის პირველი პუნქტის „ბ“ ქვეპუნქტის თანახმად, ავტომაგისტრალზე, ავტომაგისტრალის შესასვლელსა და გამოსასვლელზე აკრძალულია  სასწავლო სვლა.\""}