{"id":25,"examTicketId":15072,"imageId":null,"question":"Nizamlayıcının siqnalı eyni zamanda bir-biri ilə kəsişən trayektoriyalar üzrə hərəkət edən relssiz nəqliyyat vasitələrinə hərəkət etməyə icazə verdiyi təqdirdə, sürücülər:","answers":[{"answer":" Tənzimlənməyən yolayrıcını keçmə qaydalarını və yolayrıcında qoyulan prioritetin işarələrini əldə rəhbər tutmalıdırlar","answerNumbering":2},{"answer":" Yalnız prioriteti müəyyən edən yol işarələmələrinin tələblərini əldə rəhbər tutmalıdırlar;","answerNumbering":1}],"rightAnswer":2,"explanation":"\"„საგზაო მოძრაობის შესახებ“ საქართველოს კანონის 36-ე მუხლის მე-3  პუნქტის „დ“ ქვეპუნქტის თანახმად, რეგულირებულ გზაჯვარედინზე, თუ მარეგულირებლის სიგნალი ერთდროულად მოძრაობის ნებას რთავს ურთიერთგადამკვეთი ტრაექტორიებით მოძრავ ურელსო სატრანსპორტო საშუალებებს, მძღოლებმა უნდა იხელმძღვანელონ არარეგულირებული გზაჯვარედინის გავლის წესებითა და გზაჯვარედინზე დაყენებული პრიორიტეტის ნიშნებით.\""}