{"id":589,"examTicketId":14678,"imageId":542,"question":"Ox istiqaməti ilə  hərəkət edən yedəkli avtomobilin  sürücüsü mexaniki nəqliyyat vasitəsinin yedəyə alması üçün  təyin olunmuş tələblərini pozurumu?","answers":[{"answer":"Pozmur","answerNumbering":2},{"answer":"Pozur","answerNumbering":1}],"rightAnswer":1,"explanation":"\"   „საგზაო მოძრაობის შესახებ“ საქართველოს კანონის 45-ე მუხლის მე-4  პუნქტის  თანახმად,  ხისტი ან მოქნილი გადაბმით ბუქსირებისას აკრძალულია მგზავრის გადაყვანა საბუქსირო ავტობუსით, ტროლეიბუსითა და სატვირთო ავტომობილის ძარათი, ხოლო ნაწილობრივი დატვირთვით ბუქსირებისას – ადამიანის ყოფნა საბუქსირო მექანიკურ სატრანსპორტო საშუალებაში, აგრეთვე მობუქსირე სატრანსპორტო საშუალების ძარაზე.\""}