{"id":569,"examTicketId":14600,"imageId":667,"question":"Verilmiş yol  nişanı:","answers":[{"answer":" Sürücüyə,   yolun ensiz  hissəsinə daxil olmasını qadağan edir,  əgər bu əks hərəkəti qəlizləşdirirsə.","answerNumbering":3},{"answer":"Sürücüyə keçəcəyi yolla hərəkət edən nəqliyyat vasitələrinə  yol verməsini  tələb edir.","answerNumbering":2},{"answer":" Ensiz  yolda hərəkət etdiyi  zaman, sürücüyə, əks  tərəfdən gələn nəqliyyat vasitəsilə müqayisədə üstünlük verir. ","answerNumbering":1}],"rightAnswer":1,"explanation":"\"„საგზაო მოძრაობის შესახებ“ საქართველოს კანონის პირველი დანართის  მე-2  თავის (პრიორიტეტის ნიშანი) 2.6 პუნქტების თანახმად საგზაო ნიშანი 2.6 „უპირატესობა შემხვედრ მოძრაობასთან” -  ანიჭებს მძღოლს უპირატესობას გზის ვიწრო მონაკვეთზე მოძრაობისას საპირისპირო მიმართულებით მოძრავ სატრანსპორტო საშუალებასთან შედარებით.\""}