{"id":459,"examTicketId":14509,"imageId":null,"question":"Транспортон фæрæзы лæууæныл лæудыл нымад цæуы, кæд æмæ:","answers":[{"answer":"Змæлд урæд æрцыд техникон æдзæттæдзинадмæ гæсгæ","answerNumbering":3},{"answer":"Змæлд рагацау барæй урæд æрцыд 5минутмæ","answerNumbering":2},{"answer":"Змæлд барæй урæд у 5 минутæй фылдæр рæстæг, кæд æмæ уый  æнæмæнгхъæугæ нæ уа бæлццæтты рахизын æмæ сбадын кæнынæн, кæнæ транспортон фæрæзы байдзаг кæнын æмæ равдæлон кæнынæн","answerNumbering":1}],"rightAnswer":1,"explanation":"\"      „საგზაო მოძრაობის შესახებ“ საქართველოს კანონის მე-5 მუხლის მე-20 პუნქტის თანახმად დგომა არის სატრანსპორტო საშუალების მოძრაობის გამიზნულად შეწყვეტა 5 წუთზე მეტი ხნით, თუ ეს აუცილებელი არ არის მგზავრთა ჩასხდომა-გადმოსხდომისათვის ან სატრანსპორტო საშუალების დატვირთვა-გადმოტვირთვისათვის.\""}