{"id":241,"examTicketId":15434,"imageId":1259,"question":"Fv8fcsh0f bfye f6`8shf “BUS”  zslfkfn`b fw`f]`f bfpu`fyf0jbn> eb :","answers":[{"answer":"(imfkf tb0fqef fnhfycgjhnn` [fh[`fuf6`f bhspreg","answerNumbering":1},{"answer":"Fvfkfys7`f6`tb fvjgtl6`tb bhspreg","answerNumbering":2},{"answer":"Fvfhihenn` fnhfycgjhnn` [fh[`fuf6`f bhspreg","answerNumbering":3}],"rightAnswer":3,"explanation":"\"„საგზაო მოძრაობის შესახებ“ საქართველოს კანონის მე-2 დანართის პირველი თავის (ჰორიზონტალური მონიშვნა) 1.23  პუნქტის თანახმად, საგზაო მონიშვნა       1.23 აღნიშნავს სპეციალურ ზოლს, რომელიც განკუთვნილია სამარშრუტო სატრანსპორტო საშუალების მოძრაობისათვის.\""}