{"id":806,"examTicketId":14618,"imageId":685,"question":"Տրված ճանապարհային նշաններից որի՞ ազդման գոտում է արգելվում կցորդով  տրակտորով երթևեկությունը:","answers":[{"answer":"Բոլոր տրված նշանների ազդման գոտում:","answerNumbering":3},{"answer":"Միայն II-ի և III-ի:","answerNumbering":2},{"answer":"Միայն I-ի III-ի:","answerNumbering":1}],"rightAnswer":3,"explanation":"\"      „საგზაო მოძრაობის შესახებ“ საქართველოს კანონის პირველი დანართის  მე-3  თავის (ამკრძალავი ნიშნები) 3.2 პუნქტის თანახმად საგზაო ნიშანი 3.2 „მოძრაობა აკრძალულია” - კრძალავს ყველა სახის სატრანსპორტო საშუალებით მოძრაობას.\\r\\n      ამავე თავის 3.6 პუნქტის თანახმად საგზაო ნიშანი 3.6 „ტრაქტორით მოძრაობა აკრძალულია” - კრძალავს ყველა სახის ტრაქტორითა და თვითმავალი მანქანებით მოძრაობას.\\r\\n      ამავე თავის 3.7 პუნქტის თანახმად საგზაო ნიშანი 3.7 „მისაბმელით მოძრაობა აკრძალულია” - კრძალავს ყველა სახის მისაბმელიანი სატვირთო ავტომობილითა და მისაბმელიანი ტრაქტორით მოძრაობას, აგრეთვე მექანიკური სატრანსპორტო საშუალების ბუქსირებას.\\r\\n\""}