{"id":828,"examTicketId":14993,"imageId":null,"question":"აუცილებელია თუ არა საგზაო-სატრანსპორტო შემთხვევის შედეგად დაშავებულის კიდურებზე სისხლდენის შემჩერებელი ლახტის დადების ზუსტი დროის აღნიშვნა?","answers":[{"answer":"აუცილებელია","answerNumbering":1},{"answer":"არ არის აუცილებელი","answerNumbering":2}],"rightAnswer":1,"explanation":"\"  საგზაო-სატრანსპორტო შემთხვევის შედეგად დაშავებულის სისხლდენის შემაჩერებელი ლახტი დადება მიზანშეწონილია კიდურის იმ ნაწილში, სადაც მხოლოდ ერთი ძვალია (მხარი, ბარძაყი). ლახტი არ იდება უშუალოდ კანზე: მის ქვეშ აუცილებლად უნდა მოთავსდეს ბამბა, ნაჭერი, ტანსაცმელი. სწორად დადებისას ჭრილობიდან წყდება სისხლდენა, პერიფერიაზე ქრება პულსაცია. აუცილებლად უნდა აღინიშნოს ლახტის დადების ზუსტი დრო.\""}