{"id":199,"examTicketId":15255,"imageId":null,"question":" „C“ კატეგორიის სატრანსპორტო საშუალების მართვის უფლების მქონე მძღოლს, აგრეთვე უფლება აქვს  მართოს „C“ კატეგორიის ავტომობილი მისაბმელით, რომლის ნებადართული მაქსიმალური მასა:","answers":[{"answer":"აღემატება 750 კგ-ს, მაგრამ არ აღემატება 3 500 კგ-ს","answerNumbering":2},{"answer":"არ აღემატება 750 კგ-ს","answerNumbering":3},{"answer":"აღემატება 750 კგ-ს","answerNumbering":1}],"rightAnswer":3,"explanation":"\" „საგზაო მოძრაობის შესახებ“ საქართველოს კანონის 54-ე მუხლის მე-2 პუნქტის „გ“ ქვეპუნქტის თანახმად, სატრანსპორტო საშუალებები, რომელთა სამართავად სავალდებულოა შესაბამისი მართვის უფლების მოპოვება, იყოფა შემდეგ კატეგორიებად:  \\r\\n გ) „C“ − ავტომობილი (გარდა იმ სატრანსპორტო საშუალებებისა, რომლებიც მიეკუთვნება „D1“ ქვეკატეგორიას ან „D“ კატეგორიას), რომლის ნებადართული მაქსიმალური მასა აღემატება 3 500 კგ-ს, აგრეთვე „C“ კატეგორიის ავტომობილი, გადაბმული მისაბმელთან, რომლის ნებადართული მაქსიმალური მასა არ აღემატება 750 კგ-ს.\\r\\n\""}