{"id":951,"examTicketId":14788,"imageId":null,"question":"დასაშვებია თუ არა სატრანსპორტო საშუალების მართვისას მძღოლის მიერ მობილური კომუნიკაციის საშუალებით სარგებლობა?","answers":[{"answer":"დასაშვებია, თუ იგი სარგებლობს მობილური კომუნიკაციის ხმამაღალი საუბრის ფუნქციით და ორივე ხელი თავისუფალი აქვს სატრანსპორტო საშუალების სამართავად","answerNumbering":2},{"answer":"დასაშვებია, თუ ერთი ხელი თავისუფალი აქვს სატრანსპორტო საშუალების სამართავად","answerNumbering":3},{"answer":"დაუშვებელია ნებისმიერ შემთხვევაში","answerNumbering":1}],"rightAnswer":2,"explanation":"\" „საგზაო მოძრაობის შესახებ“ საქართველოს კანონის 21-ე მუხლის მე-8 პუნქტის თანახმად, სატრანსპორტო საშუალების გადაადგილებისას მძღოლი უნდა მოერიდოს ნებისმიერ მოქმედებას, რომელიც დაკავშირებული არ არის მართვასთან. მძღოლს ეკრძალება სატრანსპორტო საშუალების მართვისას მობილური კომუნიკაციის საშუალებით სარგებლობა. ეს აკრძალვა არ ვრცელდება ისეთ შემთხვევებზე, როდესაც მძღოლი სარგებლობს მობილური კომუნიკაციის საშუალების ყურსასმენით ან მობილური კომუნიკაციის ხმამაღალი (ან დისტანციური) საუბრის ფუნქციით და ორივე ხელი თავისუფალი აქვს სატრანსპორტო საშუალების სამართავად.\""}