{"id":709,"examTicketId":14788,"imageId":null,"question":"Допустимо или нет, при управлении транспортным средством водителем пользование средством мобильной коммуникации?","answers":[{"answer":"Допустимо, если одна рука свободна для управления транспортным средством","answerNumbering":3},{"answer":"Допустимо, если он пользуется функцией громкоговорителя мобильной коммуникации и обе руки свободны для управления транспортным средством","answerNumbering":2},{"answer":"Недопустимо в любом случае","answerNumbering":1}],"rightAnswer":2,"explanation":"\" „საგზაო მოძრაობის შესახებ“ საქართველოს კანონის 21-ე მუხლის მე-8 პუნქტის თანახმად, სატრანსპორტო საშუალების გადაადგილებისას მძღოლი უნდა მოერიდოს ნებისმიერ მოქმედებას, რომელიც დაკავშირებული არ არის მართვასთან. მძღოლს ეკრძალება სატრანსპორტო საშუალების მართვისას მობილური კომუნიკაციის საშუალებით სარგებლობა. ეს აკრძალვა არ ვრცელდება ისეთ შემთხვევებზე, როდესაც მძღოლი სარგებლობს მობილური კომუნიკაციის საშუალების ყურსასმენით ან მობილური კომუნიკაციის ხმამაღალი (ან დისტანციური) საუბრის ფუნქციით და ორივე ხელი თავისუფალი აქვს სატრანსპორტო საშუალების სამართავად.\""}