{"id":179,"examTicketId":15450,"imageId":1275,"question":"Кæцы транспортон фæрæзы скъæрæгæн фæзындзæн фæндаг раттыны хæсдзинад фатæджы (стрелкæйы) æрдæмадмæ змæлды цауы?","answers":[{"answer":"Рог автомобилы скъæрæгæн","answerNumbering":1},{"answer":"Тракторы  скъæрæгæн","answerNumbering":2}],"rightAnswer":2,"explanation":"\" „საგზაო მოძრაობის შესახებ“ საქართველოს კანონის 36-ე მუხლის მე-4 პუნქტის „გ“ ქვეპუნქტის თანახმად, არარეგულირებულ გზაჯვარედინზე, თანაბარმნიშვნელოვანი გზების გადაკვეთაზე ურელსო სატრანსპორტო საშუალების მძღოლი ვალდებულია გზა დაუთმოს მარჯვნიდან მოახლოებულ სატრანსპორტო საშუალებას.\""}