{"id":593,"examTicketId":14640,"imageId":504,"question":" Цы фæткыл хъуамæ ахизой алвæндаг (перекресток) транспортон фæрæзтæ фатæджы (стрелкæйы) æрдæмадмæ змæлды цауы?","answers":[{"answer":"Нырма хъуамæ ахиза трамвайы, стæй – рог автомобиль, уый фæстæ – мопед","answerNumbering":3},{"answer":"Нырма хъуамæ ахиза трамвайы,  стæй – мопед, уый фæстæ – рог автомобиль","answerNumbering":2},{"answer":"Нырма хъуамæ ахиза мопед, стæй – трамвайы, уый фæстæ – рог автомобиль","answerNumbering":1}],"rightAnswer":2,"explanation":"\"„საგზაო მოძრაობის შესახებ“ საქართველოს კანონის 36-ე მუხლის მე-4 პუნქტის „ა“ და „დ“ ქვეპუნქტების თანახმად: \\r\\n   ა) არათანაბარმნიშვნელოვანი გზების გადაკვეთაზე მეორეხარისხოვან გზაზე მოძრავი სატრანსპორტო საშუალების მძღოლი ვალდებულია გზა დაუთმოს მთავარი გზიდან მოახლოებულ სატრანსპორტო საშუალებას, მიუხედავად მისი შემდგომი მოძრაობის მიმართულებისა;\\r\\n   დ) მარცხნივ მოხვევისას ან მობრუნებისას ურელსო სატრანსპორტო საშუალების მძღოლი ვალდებულია გზა დაუთმოს თანაბარმნიშვნელოვან გზაზე საპირისპირო მიმართულებიდან პირდაპირ ან მარჯვნივ მოძრავ სატრანსპორტო საშუალებას. ამავე წესით უნდა იხელმძღვანელონ ურთიერთშორის რელსიანი სატრანსპორტო საშუალებების მძღოლებმაც.\\r\\n\""}