{"id":328,"examTicketId":15656,"imageId":89,"question":"Yük avtomobilinin sürücüsü ox istiqamətində hərəkət etdiyi halda, hansı avtomobilin sürücüsünə yol verməlidir?","answers":[{"answer":" Həm minik avtomobilinin, həm də avtobusun sürücüsünə.","answerNumbering":3},{"answer":" Ancaq avtobusun sürücüsünə.","answerNumbering":2},{"answer":" Ancaq minik avtomobilinin sürücüsünə.","answerNumbering":1}],"rightAnswer":2,"explanation":"\"„საგზაო მოძრაობის შესახებ“ საქართველოს კანონის 36-ე მუხლის მე-4 პუნქტის „ა“ და „დ“  ქვეპუნქტების თანახმად, არარეგულირებულ გზაჯვარედინზე:\\r\\n         ა) არათანაბარმნიშვნელოვანი გზების გადაკვეთაზე მეორეხარისხოვან გზაზე მოძრავი სატრანსპორტო საშუალების მძღოლი ვალდებულია გზა დაუთმოს მთავარი გზიდან მოახლოებულ სატრანსპორტო საშუალებას, მიუხედავად მისი შემდგომი მოძრაობის მიმართულებისა;\\r\\n         დ) მარცხნივ მოხვევისას ან მობრუნებისას ურელსო სატრა¬ნსპორტო საშუალების მძღოლი ვალდებულია გზა დაუთმოს თანაბარ¬მნიშვნელოვან გზაზე საპირისპირო მიმართულებიდან პირდაპირ ან მარჯვნივ მოძრავ სატრანსპორტო საშუალებას. ამავე წესით უნდა იხელმძღვანელონ ურთიერთშორის რელსიანი სატრანსპორტო საშუალებების მძღოლებმაც.\\r\\n\""}