{"id":510,"examTicketId":14527,"imageId":375,"question":"В данной ситуации, водитель проехавший поворот, с целью въехать в правый поворот:  ","answers":[{"answer":"Движение запрещается, как в направление А, так и в направление В","answerNumbering":4},{"answer":"Имеет право двигаться, как в направление А, так и в направление В","answerNumbering":3},{"answer":"Имеет право двигаться задним ходом в направление В","answerNumbering":2},{"answer":"Имеет право развернуть автомобиль в направление А","answerNumbering":1}],"rightAnswer":4,"explanation":"\"„საგზაო მოძრაობის შესახებ“ საქართველოს კანონის 32-ე მუხლის მე-16 პუნქტის  თანახმად, მძღოლი, რომელიც მობრუნებას ან უკუსვლით მოძრაობას აპირებს, უნდა დარწმუნდეს, რომ მას შეუძლია ისე შეასრულოს ეს მანევრი, რომ საფრთხე არ შეუქმნას და ხელი არ შეუშალოს სხვა საგზაო მოძრაობის მონაწილეებს. აუცილებლობის შემთხვევაში მიზანშეწონილია სხვა პირის დახმარება. აკრძალულია უკუსვლით მოძრაობა გზაჯვარედინზე, ავტომაგისტრალზე და ამ მუხლის მე-15 პუნქტით განსაზღვრულ ადგილებში.\\r\\n   ამავე კანონის პირველი დანართის მე-4 თავის (მიმთითებელი ნიშნები) 4.1.4 პუნქტის და ამავე პუნქტის შენიშვნის თანახმად საგზაო ნიშანი 4.1.4 „მოძრაობა პირდაპირ ან მარჯვნივ” - რთავს მხოლოდ ისრებით ნაჩვენები მიმართულებებით მოძრაობის ნებას.\\r\\n\\r\\n\""}