{"id":100,"examTicketId":15173,"imageId":1182,"question":"Verilmiş yol işarəsi məlumat verir:","answers":[{"answer":" Patrul polisi postunun olması haqqında.","answerNumbering":1},{"answer":" Qəza xidməti ilə radioəlaqə zonasının olması haqqında.","answerNumbering":2}],"rightAnswer":1,"explanation":"\"„საგზაო მოძრაობის შესახებ“ საქართველოს კანონის პირველი დანართის მე-6 თავის (სერვისის ნიშნები) 6.11 პუნქტის თანახმად, საგზაო ნიშანი 6.11 „საპატრულო პოლიციის საგუშაგო” საგზაო მოძრაობის მონაწილეებს აძლევენ  ინფორმაციას შესაბამისი ობიექტის ან სერვისის შესახებ.\""}