{"id":557,"examTicketId":14700,"imageId":null,"question":"Если фактическая масса механического транспортного средства имеющего бездействующую тормозную систему, превышает половины фактической массы буксирующего транспортного средства, его буксировка:","answers":[{"answer":"Допустима","answerNumbering":2},{"answer":"Запрещена","answerNumbering":1}],"rightAnswer":1,"explanation":"\"„საგზაო მოძრაობის შესახებ“ საქართველოს კანონის 45-ე მუხლის მე-6 პუნქტის „გ“ ქვეპუნქტის თანახმად, აკრძალულია ბუქსირება უმოქმედო სამუხრუჭო სისტემის მქონე მექანიკური სატრანსპორტო საშუალებისა, თუ მისი ფაქტობრივი მასა მობუქსირე სატრანსპორტო საშუალების ფაქტობრივი მასის ნახევარს აღემატება, ხოლო თუ მასა ნაკლებია, ბუქსირება დასაშვებია მხოლოდ ხისტი გადაბმით ან ნაწილობრივი დატვირთვით.\""}