{"id":499,"examTicketId":14692,"imageId":null,"question":"სავალდებულოა თუ არა, ხისტი გადაბმით ბუქსირებისას, საბუქსირო სატრანსპორტო საშუალებას მართავდეს მძღოლი, როცა გადაბმის კონსტრუქცია უზრუნველყოფს საბუქსირო სატრანსპორტო საშუალების მობუქსირე ტრანსპორტის ტრაექტორიით მიყოლას? ","answers":[{"answer":"არ არი სავალდებულო","answerNumbering":2},{"answer":"სავალდებულოა","answerNumbering":1}],"rightAnswer":2,"explanation":"\"„საგზაო მოძრაობის შესახებ“ საქართველოს კანონის 45-ე მუხლის მე-3 პუნქტის თანახმად, მექანიკური სატრანსპორტო საშუალების ხისტი ან მოქნილი გადაბმით ბუქსირებისას საბუქსირო სატრანსპორტო საშუალებას მძღოლი უნდა მართავდეს, გარდა იმ შემთხვევისა, როცა მოძრაობისას ხისტი გადაბმის კონსტრუქცია უზრუნველყოფს საბუქსირო სატრანსპორტო საშუალების მობუქსირე სატრანსპორტო საშუალების ტრაექტორიით მიყოლას.\""}