{"id":65,"examTicketId":15134,"imageId":1017,"question":"ოპერატიული სამსახურის ავტომობილი გაჩერებულია ჩართული ლურჯი მოელვარე სპეციალური ციმციმა სიგნალით. მსუბუქი ავტომობილის მძღოლმა უნდა იმოძრაოს არა უმეტეს:","answers":[{"answer":"70 კმ/სთ სიჩქარით","answerNumbering":2},{"answer":"იმ სიჩქარით, რომლითაც აუცილებლობის შემთხვევაში ავტომობილის დაუყონებლივ გაჩერების შესაძლებლობა ექნება","answerNumbering":3},{"answer":"90 კმ/სთ სიჩქარით","answerNumbering":1}],"rightAnswer":3,"explanation":"\"„საგზაო მოძრაობის შესახებ“ საქართველოს კანონის 51-ე მუხლის მე-3 პუნქტის თანახმად, ჩართული ლურჯი მოელვარე სპეციალური ციმციმა სიგნალით მდგომ სატრანსპორტო საშუალებასთან მიახლოებისას მძღოლმა უნდა შეანელოს სიჩქარე, რათა აუცილებლობის შემთხვევაში შეძლოს ტრანსპორტის დაუყოვნებლივ გაჩერება.\""}