{"id":684,"examTicketId":14738,"imageId":602,"question":"Which of these traffic signs must be posted twice in a non-built-up area?","answers":[{"answer":"II and IV","answerNumbering":4},{"answer":"All of them","answerNumbering":3},{"answer":"I and III","answerNumbering":2},{"answer":"I and II","answerNumbering":1}],"rightAnswer":2,"explanation":"\"„საგზაო მოძრაობის შესახებ“ საქართველოს კანონის პირველი დანართის  პირველი  თავის (მაფრთხილებელი ნიშნები) შენიშვნის „ბ“ ქვეპუნქტის თანახმად  1.2 „რკინიგზის უშლაგბაუმო გადასასვლელი” და 1.11 „სანაპიროზე გასასვლელი” ნიშნები მეორდება დაუსახლებულ პუნქტში. მეორე ნიშანი იდგმება სახიფათო მონაკვეთის დასაწყისიდან არანაკლებ 50 მეტრ მანძილზე.\""}