{"id":581,"examTicketId":14361,"imageId":230,"question":"„CE“ frfntujhbf bfqfyfr`f  fblfhfn` vfimsyf cff0rfkf @% rv. fkfchfkf tb0fqefpfh> f[sw f[sh[fh0fkf fb0fqhffy f,fh0 fnhfycgjhnn` [fh[`fuf6`f hshys7`f8w`f h7syn` fv8fn` fb0fqhf fqfc6`f tbkfpujlf? ","answers":[{"answer":"Fblfhfn` vfimsytb fdnj,ecb hshys7`f8w`f","answerNumbering":4},{"answer":"Fnhfrnjhb fblfhfn` vfimsytb hshys7`f8w`f","answerNumbering":3},{"answer":"Fblfhfn` vfimsyf fhys7`f8 pfq`s","answerNumbering":2},{"answer":"Fnhfrnjh fhys7`f8 pfq`s","answerNumbering":1}],"rightAnswer":3,"explanation":"\"„საგზაო მოძრაობის შესახებ“ საქართველოს კანონის 38-ე მუხლის პირველი პუნქტის „ა“ და „გ.გ“ ქვეპუნქტების თანახმად, ავტომაგისტრალზე, ავტომაგისტრალის შესასვლელსა და  გამოსასვლელზე:\\r\\nა) აკრძალულია ქვეითის, ცხოველის, ველოსიპედის, მოპედის, ორბორბლიანი ელექტროთვითმგორავის, ავტომობილისა და მათი მისაბმელებისგან განსხვავებული ყველა სატრანსპორტო საშუალების მოძრაობა.\\r\\nგ.გ) მძღოლს ეკრძალება მეორე ზოლის იქით იმ ტვირთის გადამზიდავი ავტომობილით (მისაბმელებით ან მათ გარეშე) მოძრაობა, რომლის ნებადართული მაქსიმალური მასა 3,5 ტონას აღემატება ან იმ მისაბმელიანი ავტომობილებით მოძრაობა,  რომელთა საერთო სიგრძე 7 მეტრზე მეტია.\\r\\n\""}