{"id":54,"examTicketId":15109,"imageId":null,"question":"На том гужевом транспорте, ширина которого не превышает одного метра, обязательно установить:","answers":[{"answer":"Сзади, в левой стороне, или в центре – одно оборудованое светоотражателя","answerNumbering":3},{"answer":"Впереди - один белый свет и сзади – один красного света","answerNumbering":2},{"answer":"Самое малое хотя бы один передний белый или желтый селекционный свет","answerNumbering":1}],"rightAnswer":3,"explanation":"\" „საგზაო მოძრაობის შესახებ“ საქართველოს კანონის 50-ე მუხლის მე-3  პუნქტის თანახმად, ფარანი არ არის აუცილებელი იმ საჭაპანო ტრანსპორტისათვის, რომლის სიგანე 1 მეტრს არ აღემატება, მაგრამ ამ შემთხვევაში უკან, მარცხენა მხარეს, ან ცენტრში დაყენებული უნდა იყოს ერთი შუქამრეკლი მოწყობილობა.\""}