{"id":232,"examTicketId":14061,"imageId":28,"question":"Ո՞ր ավտոմեքենայի վարորդի մոտ կառաջանա ճանապարհը զիջելու պարտավորություն, սլաքի ուղղությամբ երթևեկելու դեպքում:","answers":[{"answer":"Ավտոբուսի վարորդի:","answerNumbering":2},{"answer":"Թեթև մարդատար ավտոմեքենայի վարորդի:","answerNumbering":1}],"rightAnswer":1,"explanation":"\"„საგზაო მოძრაობის შესახებ“ საქართველოს კანონის 36-ე მუხლის მე-4 პუნქტის „ა“ ქვეპუნქტის თანახმად, არარეგულირებულ გზაჯვარედინზე, არათანაბარმნიშვნელოვანი გზების გადაკვეთაზე მეორეხარისხოვან გზაზე მოძრავი სატრანსპორტო საშუალების მძღოლი ვალდებულია გზა დაუთმოს მთავარი გზიდან მოახლოებულ სატრანსპორტო საშუალებას, მიუხედავად მისი შემდგომი მოძრაობის მიმართულებისა.\""}