{"id":265,"examTicketId":15687,"imageId":54,"question":"Fblfhfn` vfimsyf  fhys7`f8 f[sw f[sh[fh0fkf ltb0fqefpfh> f,fh0 fnhfycgjhnn` [fh[`fuf6`f hshys7`f8w`f h7syn` fv8f f0fhf ps[`0flf>  fh/mfhf[mn`b fufyf7syn` fv8tb[scsh0f bfkfkj fv8f fysi` bf6`pfh?","answers":[{"answer":"Fdnj,ec fhys7`f8b> bfhf e,fc> fvjnjwbrk fhys7`f8b","answerNumbering":3},{"answer":"Fvjnjwbrk fhys7`f8 pfq`s","answerNumbering":2},{"answer":"Fdnj,ec fhys7`f8 pfq`s","answerNumbering":1}],"rightAnswer":2,"explanation":"\"„საგზაო მოძრაობის შესახებ“ საქართველოს კანონის 36-ე მუხლის მე-4 პუნქტის „გ“ ქვეპუნქტის თანახმად, არარეგულირებულ გზაჯვარედინზე, თანაბარმნიშვნელოვანი გზების გადაკვეთაზე ურელსო სატრანსპორტო საშუალების მძღოლი ვალდებულია გზა დაუთმოს მარჯვნიდან მოახლოებულ სატრანსპორტო საშუალებას. ამავე წესით უნდა ხელმძღვანელონ ურთიერთშორის რელსიანი სატრანსპორტო საშუალებების მძღოლებმაც. ასეთ გზაჯვარედინზე რელსიან სატრანსპორტო საშუალებას უპირატესობა აქვს ურელსო სატრანსპორტო საშუალების მიმართ, მიუხედავად მისი მოძრაობის მიმართულებისა.\\r\\n ამავე მუხლის მე-6 პუნქტის თანახმად, თუ საგზაო ნიშნით სხვა რამ არ არის გათვალისწინებული, გრუნტოვანი გზიდან იმ გზაზე გასვლისას, რომელიც არ არის გრუნტოვანი გზა, მძღოლი ვალდებულია გზა დაუთმოს ამ გზაზე მოძრავ სატრანსპორტო საშუალებას.\\r\\n  ამავე კანონის მე-5 მუხლის 37-ე პუნქტის თანახმად ღორღიან ან გრუნტოვან გზაზე უშუალოდ გზაჯვარედინის წინ, გზის მკვრივსაფარიანი უბნის არსებობა არ ათანაბრებს მას მკვრივსაფარიან გზასთან.\\r\\n\""}