{"id":497,"examTicketId":14513,"imageId":361,"question":"Bfh,je f0fuskfpffimf=s> fnhfycgjhnn` [fh[`fuf6`f ffv0frfkf fb0fqhfn` w`f]`f6`f hs9cf[sh> fbfchf f9s;`fhf bjejbn:","answers":[{"answer":"Fblfhfn` vfimsyf fhys7`f8","answerNumbering":2},{"answer":"Fvfimsyf kfc fhys7`f8","answerNumbering":1}],"rightAnswer":1,"explanation":"\" „საგზაო მოძრაობის შესახებ“ საქართველოს კანონის 32-ე მუხლის მე-4 პუნქტის  თანახმად, მოძრაობის მიმართულების შეუცვლელად მოძრაობის ზოლიდან ზოლში გადასვლისას, მძღოლმა გზა უნდა დაუთმოს გადასასვლელ მოძრაობის ზოლში თანმხვედრი მიმართულებით მოძრავ სატრანსპორტო საშუალებას. თანმხვედრი მიმართულებით მოძრავი სატრანსპორტო საშუალებების მიერ, მოძრაობის ზოლების ერთდროულად შეცვლისას, მოძრაობის  ტრაექტორიების გადაკვეთის შემთხვევაში, გავლის უპირატესობა ენიჭება მარჯნივ მყოფ სატრანსპორტო საშუალების მძღოლს.\\r\\n\\r\\n\""}