{"id":485,"examTicketId":14349,"imageId":null,"question":"Կարգավորողի կողմից սուլիչով տրված լրացուցիչ ազդանշանը.","answers":[{"answer":"Զգուշացնում է մոտեցած վտանգի մասին:","answerNumbering":4},{"answer":"Տալիս է երթևեկության իրավունք:","answerNumbering":3},{"answer":"Ուղղված է երթևեկության մասնակիցների ուշադրության հրավիրմանը:","answerNumbering":2},{"answer":"Արգելում է երթևեկությունը:","answerNumbering":1}],"rightAnswer":2,"explanation":"\"„საგზაო მოძრაობის შესახებ“ საქართველოს კანონის 30-ე მუხლის მე-10 პუნქტის თანახმად, მარეგულირებლის მიერ სასტვენით მიცემული დამატებითი სიგნალი გამიზნულია მოძრაობის მონაწილეების ყურადღების მისაპყრობად.\""}