{"id":1171,"examTicketId":15733,"imageId":null,"question":"Кæд уæлæфтау гæххæтты (накладная) нæу нысангод уаргъласыны уавæртæ, уæд йе сбæлвырдмæ нысан кæны, цæмæй:","answers":[{"answer":"Уаргъласæгæй уаргъ райсгæйæ уаргъ æмæ йæ тыхт (упаковкæ) æддаг бакастæй хорз уавæры кæй уыди æмæ кæй у уаргъы иугайон бæрцад, уый бæрджытæ æмæ номыртæ кæрæдзимæ æнгæс сты уæлæфтау гæххæтты (накладная) фыст бæрæггæнæнтимæ.","answerNumbering":1},{"answer":" Уаргъласæг нæдæр уæлæфтау гæххæтты (накладная) æмæ нæдæр уаргъы нæ райста. \r\n\r\n","answerNumbering":3},{"answer":" Уаргъласæг уаргъы нæ райста. ","answerNumbering":2}],"rightAnswer":1,"explanation":"\"საქართველოს სამოქალაქო კოდექსის 677-ე მუხლის მე-2 პუნქტის თანახმად, თუ ზედნადებში არ არის აღნიშნული გადაზიდვის პირობები, საპირისპიროს დამტკიცებამდე ივარაუდება, რომ გადამზიდველის მიერ ტვირთის მიღებისას ტვირთი და მისი შეფუთვა გარეგნულად კარგ მდგომარეობაში იყო და რომ ტვირთის ცალობრივი რაოდენობა, მისი აღნიშვნები და ნომრები ემთხვევა ზედნადებში ჩაწერილ მონაცემებს. \""}