{"id":465,"examTicketId":14221,"imageId":291,"question":"Ис æви нæ бар уæзласæн автомобилы скъæрæгæн райдайа разæй кæныны (обгоны) маневр, кæд æмæ рог автомобилы  скъæрæгæн иугонд ис галиумæ фæзилæны æвдисæг æмæ хъуамæ фæразæй уа?","answers":[{"answer":"Ис ын бар","answerNumbering":2},{"answer":"Нæй ын бар","answerNumbering":1}],"rightAnswer":1,"explanation":"\"„საგზაო მოძრაობის შესახებ“ საქართველოს კანონის 34-ე მუხლის მე-3 პუნქტის „ა“ ქვეპუნქტის თანახმად, გასწრების დაწყებამდე მძღოლი, ისე, რომ არ დაარღვიოს ამ კანონის მე-20 მუხლის მე-2 პუნქტითა და 32-ე მუხლით დადგენილი მოთხოვნები, უნდა დარწმუნდეს, რომ მის უკან მომავალი არცერთი სატრანსპორტო საშუალების მძღოლს გასწრება არ დაუწყია.\""}