{"id":236,"examTicketId":14102,"imageId":69,"question":"რა თანამიმდევრობით უნდა გაიარონ გზაჯვარედინი სატრანსპორტო საშუალებებმა ისრის მიმართულებით მოძრაობის შემთხვევაში?","answers":[{"answer":"ჯერ უნდა გაიაროს მეორე ტრამვაიმ, შემდეგ - მსუბუქმა ავტომობილმა, ბოლოს - პირველმა ტრამვაიმ","answerNumbering":2},{"answer":"ჯერ უნდა გაიაროს პირველმა ტრამვაიმ, შემდეგ - მეორე ტრამვაიმ, ბოლოს - მსუბუქმა ავტომობილმა","answerNumbering":3},{"answer":"ჯერ უნდა გაიაროს მსუბუქმა ავტომობილმა, შემდეგ - პირველმა ტრამვაიმ, ბოლოს - მეორე ტრამვაიმ","answerNumbering":1}],"rightAnswer":3,"explanation":"\"„საგზაო მოძრაობის შესახებ“ საქართველოს კანონის 36-ე მუხლის მე-4 პუნქტის „გ“ ქვეპუნქტის თანახმად, არარეგულირებულ გზაჯვარედინზე,       თანაბარმნიშვნელოვანი გზების გადაკვეთაზე ურელსო სატრანსპორტო საშუალების მძღოლი ვალდებულია გზა დაუთმოს მარჯვნიდან მოახლოებულ სატრანსპორტო საშუალებას. ამავე წესით უნდა იხელმძღვანელონ ურთიერთშორის რელსიანი სატრანსპორტო საშუალებების მძღოლებმაც. ასეთ გზაჯვარედინზე რელსიან სატრანსპორტო საშუალებას უპირატესობა აქვს ურელსო სატრანსპორტო საშუალების მიმართ, მიუხედავად მისი მოძრაობის მიმართულებისა.\""}